fanart/__init__.py
fanart/core.py
fanart/errors.py
fanart/immutable.py
fanart/items.py
fanart/movie.py
fanart/music.py
fanart/tv.py
fanart/tests/__init__.py
fanart/tests/test_core.py
fanart/tests/test_immutable.py
fanart/tests/test_items.py
fanart/tests/test_movie.py
fanart/tests/test_music.py
fanart/tests/test_tv.py
python3_fanart-2.0.0.dist-info/LICENSE
python3_fanart-2.0.0.dist-info/METADATA
python3_fanart-2.0.0.dist-info/WHEEL
python3_fanart-2.0.0.dist-info/top_level.txt
python3_fanart-2.0.0.dist-info/RECORD
