Metadata-Version: 1.2
Name: python3-fanart
Version: 2.0.0
Summary: Python3 interface to fanart.tv API (v3)
